{"vfiV2UXItv7YLRfT7M1eaQ==":"mbr-96x96.png","NxkcG9Ma9KNPXqk+BEdhxw==":"mbr-1920x1079.jpg","SJTwvmOAXTDaIfX3nTpDVg==":"mbr-816x397.jpg","Vs557l58vlkr83zK5B0uDQ==":"mbr-816x544.jpg","HUNdswTRH3r9os4MX60mvw==":"mbr-816x545.jpg","bMDQKnUm52k/HCQdSuBa5g==":"mbr-1476x1195.jpg","KcEt9H/QJVCwoD2smwlYkw==":"mbr-838x602.jpg","x1wOkYyKF/eCFhjteG4ASg==":"mbr-838x560.jpg","hqvLtdIwFiKgEjQed/O01Q==":"mbr-838x598.jpg","fJpJKzRAiiyBQk8HUW+9jA==":"mbr-838x1053.jpg","pR+U7VcSZ5WdOCPUQZPNyg==":"mbr-838x629.jpg","8FLLIEaQJZX+eblvbJMynQ==":"mbr-838x559.jpg","yYZqMWUQ1AlIjvHZzXXWaw==":"mbr-1-838x559.jpg","TutOfveBuNrWEHGHUgatwg==":"mbr-179x156.jpg","c8T+7IsNBongs4qfS5TKkQ==":"mbr-179x119.jpg","d6D5j1Fg3Ayz/FKxUPGeAw==":"mbr-179x270.jpeg","jyANXVCds82ZtrjlkodZ3g==":"mbr-179x119.jpeg","1JTV/i+xBFlFxtq4A8RaBg==":"mbr-179x156.jpeg"}